{
	"children_yay": {"description": "Children cheering once when the birthday card appears.", "loop": false, "path": "res://assets/shared/audio/sfx/children_yay.mp3", "type": "sfx"},
	"literally_my_life": {"description": "The single looping story track, stopped after SRMT is defeated.", "loop": true, "path": "res://assets/shared/audio/music/literally_my_life.mp3", "type": "music"},
	"banana_gun": {"description": "Banana gun curved shot cue.", "loop": false, "path": "res://assets/shared/audio/sfx/banana_gun.wav", "type": "sfx"},
	"battle_phase": {"description": "Battle phase change cue.", "loop": false, "path": "res://assets/shared/audio/sfx/battle_phase.wav", "type": "sfx"},
	"berry_potion": {"description": "Berry potion splash and heal cue.", "loop": false, "path": "res://assets/shared/audio/sfx/berry_potion.wav", "type": "sfx"},
	"boss_defeat": {"description": "Boss defeat collapse cue.", "loop": false, "path": "res://assets/shared/audio/sfx/boss_defeat.wav", "type": "sfx"},
	"boss_hurt": {"description": "Boss hurt impact cue.", "loop": false, "path": "res://assets/shared/audio/sfx/boss_hurt.wav", "type": "sfx"},
	"building_break": {"description": "Building collapse crunch cue.", "loop": false, "path": "res://assets/shared/audio/sfx/building_break.wav", "type": "sfx"},
	"clue_pickup": {"description": "Clue pickup cue.", "loop": false, "path": "res://assets/shared/audio/sfx/clue_pickup.wav", "type": "sfx"},
	"door_slam": {"description": "Heavy door slam cue.", "loop": false, "path": "res://assets/shared/audio/sfx/door_slam.wav", "type": "sfx"},
	"growth_transform": {"description": "Shrububu growth transformation cue.", "loop": false, "path": "res://assets/shared/audio/sfx/growth_transform.wav", "type": "sfx"},
	"guitar_note": {"description": "Musical guitar note cue.", "loop": false, "path": "res://assets/shared/audio/sfx/guitar_note.wav", "type": "sfx"},
	"revolver": {"description": "Poojan revolver shot cue.", "loop": false, "path": "res://assets/shared/audio/sfx/revolver.wav", "type": "sfx"},
	"transition_wipe": {"description": "Scene transition wipe cue.", "loop": false, "path": "res://assets/shared/audio/sfx/transition_wipe.wav", "type": "sfx"}
}
